<?xml version="1.0" encoding="UTF-8"?>
<SpectralIndex>
    <Name>ARI,ARI1</Name>
    <Wavelengths>
        <Band name="R550" min="550" max="550" unit="nm"/>
        <Band name="R700" min="700" max="700" unit="nm"/>
    </Wavelengths>
    <MathML>
        <math xmlns="http://www.w3.org/1998/Math/MathML">
            <apply>
                <minus/>
                <apply>
                    <divide/>
                    <cn>1.0</cn>
                    <ci>R550</ci>
                </apply>
                <apply>
                    <divide/>
                    <cn>1.0</cn>
                    <ci>R700</ci>
                </apply>
            </apply>
        </math>
    </MathML>
    <Metadata>
        <Description>Anthocyanin Reflectance Index 1 (ARI1)</Description>
    </Metadata>
</SpectralIndex>